drf_localize/__init__.py
drf_localize/applications/__init__.py
drf_localize/applications/helpers.py
drf_localize/applications/managers.py
drf_localize/applications/mixins.py
drf_localize/applications/permissions.py
drf_localize/applications/serializers.py
drf_localize/applications/views.py
drf_localize/asgi.py
drf_localize/commons/__init__.py
drf_localize/commons/errors.py
drf_localize/commons/helpers/__init__.py
drf_localize/commons/helpers/classes.py
drf_localize/commons/helpers/views.py
drf_localize/commons/permissions.py
drf_localize/commons/serializers.py
drf_localize/commons/views.py
drf_localize/core/__init__.py
drf_localize/fixtures/__init__.py
drf_localize/fixtures/localizekeys.json
drf_localize/fixtures/localizelanguages.json
drf_localize/helpers.py
drf_localize/middlewares.py
drf_localize/migrations/0001_initial.py
drf_localize/migrations/__init__.py
drf_localize/models.py
drf_localize/serializers.py
drf_localize/settings.py
drf_localize/urls.py
drf_localize-0.1.5.dist-info/LICENSE.md
drf_localize-0.1.5.dist-info/WHEEL
drf_localize-0.1.5.dist-info/METADATA
drf_localize-0.1.5.dist-info/RECORD
