Metadata-Version: 2.1
Name: drf-localize
Version: 0.1.5
Summary: Package to provide localization experiences for mobile and api applications.
License: MIT
Author: Dorin Musteața
Requires-Python: >=3.7,<=3.10
Classifier: License :: OSI Approved :: MIT License
Classifier: Programming Language :: Python :: 3
Classifier: Programming Language :: Python :: 3.7
Classifier: Programming Language :: Python :: 3.8
Classifier: Programming Language :: Python :: 3.9
Requires-Dist: Django (>=3.2.8,<4.0.0)
Requires-Dist: django-cors-headers (>=3.10.0,<4.0.0)
Requires-Dist: django-filter (>=21.1,<22.0)
Requires-Dist: djangorestframework (>=3.12.4,<4.0.0)
Requires-Dist: drf-yasg (>=1.20.0,<2.0.0)
Requires-Dist: jsonschema (>=3.2.0,<4.0.0)
Requires-Dist: swagger_spec_validator (>=2.7.4,<3.0.0)
